x_series/__init__.py
x_series/__main__.py
x_series/cli.py
x_series/utils.py
x_series/x_series.py
x_series-0.1.0.dist-info/entry_points.txt
x_series-0.1.0.dist-info/licenses/LICENSE
x_series-0.1.0.dist-info/METADATA
x_series-0.1.0.dist-info/WHEEL
x_series-0.1.0.dist-info/RECORD
