Metadata-Version: 2.4
Name: x-series
Version: 0.1.0
Summary: Modular Python utilities for entity extraction, validation, and graph-ready data pipelines — built for LLM and data engineering workflows.
License: MIT
License-File: LICENSE
Author: Mahmoud Lotfi
Author-email: mlotfic@gmail.com
Maintainer: Mahmoud Lotfi
Maintainer-email: mlotfic@gmail.com
Requires-Python: >= 3.10
Classifier: License :: OSI Approved :: MIT License
Classifier: Programming Language :: Python :: 3
Classifier: Programming Language :: Python :: 3.10
Classifier: Programming Language :: Python :: 3.11
Classifier: Programming Language :: Python :: 3.12
Classifier: Programming Language :: Python :: 3.13
Classifier: Programming Language :: Python :: 3.14
Provides-Extra: test
Requires-Dist: coverage ; extra == "test"
Requires-Dist: ipdb ; extra == "test"
Requires-Dist: pytest ; extra == "test"
Requires-Dist: ruff ; extra == "test"
Requires-Dist: ty ; extra == "test"
Requires-Dist: typer
Project-URL: Homepage, https://github.com/mlotfic/x-series
Project-URL: Repository, https://github.com/mlotfic/x-series
Project-URL: bugs, https://github.com/mlotfic/x-series/issues
Project-URL: changelog, https://github.com/mlotfic/x-series/releases
